mathml2docx/MML2OMML.XSL
mathml2docx/__init__.py
mathml2docx/config.py
mathml2docx/h2d.py
mathml2docx/utils.py
mathml2docx/wrapper.py
mathml2docx-0.1.3.dist-info/LICENSE
mathml2docx-0.1.3.dist-info/METADATA
mathml2docx-0.1.3.dist-info/WHEEL
mathml2docx-0.1.3.dist-info/top_level.txt
mathml2docx-0.1.3.dist-info/RECORD
