Metadata-Version: 2.1
Name: mathml2docx
Version: 0.1.3
Summary: The fork in https://github.com/pqzx/html2docx converts html (including mathml) to docx
Author: joongi007
License: MIT License
Project-URL: Repository, https://github.com/joongi007/mathml2docx
Keywords: html,mathml,docx,convert
Classifier: License :: OSI Approved :: MIT License
Requires-Python: >=3.6
License-File: LICENSE
Requires-Dist: beautifulsoup4 ==4.8.0
Requires-Dist: python-docx ==1.1.0
